expect_exception/__init__.py
expect_exception/_contextmanagers.py
expect_exception/_enums.py
expect_exception/_errors.py
tests/__init__.py
tests/expect_exception_test.py
expect_exception-1.0.2.dist-info/LICENSE
expect_exception-1.0.2.dist-info/METADATA
expect_exception-1.0.2.dist-info/WHEEL
expect_exception-1.0.2.dist-info/top_level.txt
expect_exception-1.0.2.dist-info/RECORD
