Metadata-Version: 2.1
Name: expect-exception
Version: 1.0.2
Summary: Context manager that expects code to raise an exception
Home-page: https://github.com/danielrozenberg/expect-exception
Author: Daniel Rozenberg
Author-email: me@danielrozenberg.com
License: ISC
Platform: any
Classifier: Development Status :: 5 - Production/Stable
Classifier: Intended Audience :: Developers
Classifier: License :: OSI Approved :: ISC License (ISCL)
Classifier: Operating System :: OS Independent
Classifier: Programming Language :: Python :: 3
Classifier: Programming Language :: Python :: 3 :: Only
Classifier: Programming Language :: Python :: 3.6
Classifier: Programming Language :: Python :: 3.7
Classifier: Programming Language :: Python :: 3.8
Classifier: Typing :: Typed
Requires-Python: >=3.6
